TCAT/TCAT.py
TCAT/__init__.py
TCAT/annotate.py
TCAT/classifier.py
TCAT/logger.py
TCAT/models.py
TCAT/data/annotation_state_correction_low_cd4_polish.pkl
TCAT/data/annotation_state_correction_low_cd8_polish_nkt.pkl
TCAT/data/annotation_state_correction_low_polish_nkt.pkl
TCAT/data/marker_combine_CD4.txt
TCAT/data/marker_combine_CD8.txt
TCATT-0.1.dist-info/METADATA
TCATT-0.1.dist-info/WHEEL
TCATT-0.1.dist-info/top_level.txt
TCATT-0.1.dist-info/RECORD
