Metadata-Version: 2.1
Name: TCATT
Version: 0.1
Requires-Python: >=3.6
Requires-Dist: numpy >=1.19.0
Requires-Dist: pandas >=1.0.5
Requires-Dist: scikit-learn >=0.24.1
Requires-Dist: openpyxl >=3.0.4
Requires-Dist: click >=7.1.2
Requires-Dist: scanpy >=1.7.0
Requires-Dist: leidenalg >=0.8.3
